[
  {
    "date": "2026-05-18",
    "stars": 52900,
    "forks": 24358,
    "watchers": 357,
    "open_issues": 861,
    "description": "Build AI Agents, Visually"
  },
  {
    "date": "2026-05-19",
    "stars": 52929,
    "forks": 24361,
    "watchers": 357,
    "open_issues": 861,
    "description": "Build AI Agents, Visually"
  },
  {
    "date": "2026-05-20",
    "stars": 52948,
    "forks": 24366,
    "watchers": 357,
    "open_issues": 861,
    "description": "Build AI Agents, Visually"
  },
  {
    "date": "2026-05-21",
    "stars": 52971,
    "forks": 24362,
    "watchers": 357,
    "open_issues": 865,
    "description": "Build AI Agents, Visually"
  },
  {
    "date": "2026-05-22",
    "stars": 52996,
    "forks": 24373,
    "watchers": 357,
    "open_issues": 868,
    "description": "Build AI Agents, Visually"
  },
  {
    "date": "2026-05-23",
    "stars": 53013,
    "forks": 24382,
    "watchers": 357,
    "open_issues": 871,
    "description": "Build AI Agents, Visually"
  },
  {
    "date": "2026-05-24",
    "stars": 53039,
    "forks": 24386,
    "watchers": 356,
    "open_issues": 872,
    "description": "Build AI Agents, Visually"
  },
  {
    "date": "2026-05-25",
    "stars": 53067,
    "forks": 24395,
    "watchers": 357,
    "open_issues": 874,
    "description": "Build AI Agents, Visually"
  },
  {
    "date": "2026-05-26",
    "stars": 53080,
    "forks": 24395,
    "watchers": 357,
    "open_issues": 875,
    "description": "Build AI Agents, Visually"
  },
  {
    "date": "2026-05-27",
    "stars": 53109,
    "forks": 24409,
    "watchers": 357,
    "open_issues": 878,
    "description": "Build AI Agents, Visually"
  },
  {
    "date": "2026-05-28",
    "stars": 53147,
    "forks": 24420,
    "watchers": 357,
    "open_issues": 882,
    "description": "Build AI Agents, Visually"
  },
  {
    "date": "2026-05-29",
    "stars": 53187,
    "forks": 24430,
    "watchers": 357,
    "open_issues": 885,
    "description": "Build AI Agents, Visually"
  },
  {
    "date": "2026-05-30",
    "stars": 53214,
    "forks": 24442,
    "watchers": 358,
    "open_issues": 887,
    "description": "Build AI Agents, Visually"
  },
  {
    "date": "2026-05-31",
    "stars": 53230,
    "forks": 24451,
    "watchers": 358,
    "open_issues": 890,
    "description": "Build AI Agents, Visually"
  },
  {
    "date": "2026-06-01",
    "stars": 53245,
    "forks": 24456,
    "watchers": 357,
    "open_issues": 879,
    "description": "Build AI Agents, Visually"
  }
]